{
"skeleton": { "hash": "c8YgGx3fhxliPxleg4Wp/SX6y4k", "spine": "3.5.37", "width": 720, "height": 1280, "images": "" },
"bones": [
	{ "name": "root" },
	{ "name": "bone_190", "parent": "root", "x": -145.34, "y": 740.41 },
	{ "name": "yj1", "parent": "bone_190", "x": 131.01, "y": -50.25 }
],
"slots": [
	{ "name": "yj1", "bone": "yj1", "attachment": "images/yj1" },
	{ "name": "yj2", "bone": "yj1", "attachment": "images/yj2" },
	{ "name": "yj3", "bone": "yj1", "attachment": "images/yj3" },
	{ "name": "yj4", "bone": "yj1", "attachment": "images/yj4" },
	{ "name": "yj5", "bone": "yj1", "attachment": "images/yj5" },
	{ "name": "yj6", "bone": "yj1", "attachment": "images/yj6" },
	{ "name": "yj7", "bone": "yj1", "attachment": "images/yj7" }
],
"skins": {
	"default": {
		"yj1": {
			"images/yj1": { "x": -7.08, "y": -74.06, "scaleX": 1.241, "scaleY": 1.241, "width": 480, "height": 198 }
		},
		"yj2": {
			"images/yj2": { "x": -7.08, "y": -74.06, "scaleX": 1.241, "scaleY": 1.241, "width": 480, "height": 198 }
		},
		"yj3": {
			"images/yj3": { "x": -7.08, "y": -74.06, "scaleX": 1.241, "scaleY": 1.241, "width": 480, "height": 198 }
		},
		"yj4": {
			"images/yj4": { "x": -7.08, "y": -74.06, "scaleX": 1.241, "scaleY": 1.241, "width": 480, "height": 198 }
		},
		"yj5": {
			"images/yj5": { "x": -7.08, "y": -74.06, "scaleX": 1.241, "scaleY": 1.241, "width": 480, "height": 198 }
		},
		"yj6": {
			"images/yj6": { "x": -7.08, "y": -74.06, "scaleX": 1.241, "scaleY": 1.241, "width": 480, "height": 198 }
		},
		"yj7": {
			"images/yj7": { "x": -7.08, "y": -74.06, "scaleX": 1.241, "scaleY": 1.241, "width": 480, "height": 198 }
		}
	}
},
"animations": {
	"animation": {
		"slots": {
			"yj1": {
				"color": [
					{ "time": 0, "color": "ffffffff", "curve": "stepped" },
					{ "time": 0.1667, "color": "ffffff00", "curve": "stepped" },
					{ "time": 0.3333, "color": "ffffff00", "curve": "stepped" },
					{ "time": 0.5, "color": "ffffff00", "curve": "stepped" },
					{ "time": 0.6667, "color": "ffffff00", "curve": "stepped" },
					{ "time": 0.8333, "color": "ffffff00", "curve": "stepped" },
					{ "time": 1, "color": "ffffff00", "curve": "stepped" },
					{ "time": 1.1667, "color": "ffffffff" }
				]
			},
			"yj2": {
				"color": [
					{ "time": 0, "color": "ffffff00", "curve": "stepped" },
					{ "time": 0.1667, "color": "ffffffff", "curve": "stepped" },
					{ "time": 0.3333, "color": "ffffff00", "curve": "stepped" },
					{ "time": 0.5, "color": "ffffff00", "curve": "stepped" },
					{ "time": 0.6667, "color": "ffffff00", "curve": "stepped" },
					{ "time": 0.8333, "color": "ffffff00", "curve": "stepped" },
					{ "time": 1, "color": "ffffff00", "curve": "stepped" },
					{ "time": 1.1667, "color": "ffffff00" }
				]
			},
			"yj3": {
				"color": [
					{ "time": 0, "color": "ffffff00", "curve": "stepped" },
					{ "time": 0.1667, "color": "ffffff00", "curve": "stepped" },
					{ "time": 0.3333, "color": "ffffffff", "curve": "stepped" },
					{ "time": 0.5, "color": "ffffff00", "curve": "stepped" },
					{ "time": 0.6667, "color": "ffffff00", "curve": "stepped" },
					{ "time": 0.8333, "color": "ffffff00", "curve": "stepped" },
					{ "time": 1, "color": "ffffff00", "curve": "stepped" },
					{ "time": 1.1667, "color": "ffffff00" }
				]
			},
			"yj4": {
				"color": [
					{ "time": 0, "color": "ffffff00", "curve": "stepped" },
					{ "time": 0.1667, "color": "ffffff00", "curve": "stepped" },
					{ "time": 0.3333, "color": "ffffff00", "curve": "stepped" },
					{ "time": 0.5, "color": "ffffffff", "curve": "stepped" },
					{ "time": 0.6667, "color": "ffffff00", "curve": "stepped" },
					{ "time": 0.8333, "color": "ffffff00", "curve": "stepped" },
					{ "time": 1, "color": "ffffff00", "curve": "stepped" },
					{ "time": 1.1667, "color": "ffffff00" }
				]
			},
			"yj5": {
				"color": [
					{ "time": 0, "color": "ffffff00", "curve": "stepped" },
					{ "time": 0.1667, "color": "ffffff00", "curve": "stepped" },
					{ "time": 0.3333, "color": "ffffff00", "curve": "stepped" },
					{ "time": 0.5, "color": "ffffff00", "curve": "stepped" },
					{ "time": 0.6667, "color": "ffffffff", "curve": "stepped" },
					{ "time": 0.8333, "color": "ffffff00", "curve": "stepped" },
					{ "time": 1, "color": "ffffff00", "curve": "stepped" },
					{ "time": 1.1667, "color": "ffffff00" }
				]
			},
			"yj6": {
				"color": [
					{ "time": 0, "color": "ffffff00", "curve": "stepped" },
					{ "time": 0.1667, "color": "ffffff00", "curve": "stepped" },
					{ "time": 0.3333, "color": "ffffff00", "curve": "stepped" },
					{ "time": 0.5, "color": "ffffff00", "curve": "stepped" },
					{ "time": 0.6667, "color": "ffffff00", "curve": "stepped" },
					{ "time": 0.8333, "color": "ffffffff", "curve": "stepped" },
					{ "time": 1, "color": "ffffff00", "curve": "stepped" },
					{ "time": 1.1667, "color": "ffffff00" }
				]
			},
			"yj7": {
				"color": [
					{ "time": 0, "color": "ffffff00", "curve": "stepped" },
					{ "time": 0.1667, "color": "ffffff00", "curve": "stepped" },
					{ "time": 0.3333, "color": "ffffff00", "curve": "stepped" },
					{ "time": 0.5, "color": "ffffff00", "curve": "stepped" },
					{ "time": 0.6667, "color": "ffffff00", "curve": "stepped" },
					{ "time": 0.8333, "color": "ffffff00", "curve": "stepped" },
					{ "time": 1, "color": "ffffffff", "curve": "stepped" },
					{ "time": 1.1667, "color": "ffffff00" }
				]
			}
		},
		"bones": {
			"yj1": {
				"rotate": [
					{ "time": 0, "angle": 0, "curve": "stepped" },
					{ "time": 0.1667, "angle": 0, "curve": "stepped" },
					{ "time": 0.3333, "angle": 0, "curve": "stepped" },
					{ "time": 0.5, "angle": 0, "curve": "stepped" },
					{ "time": 0.6667, "angle": 0, "curve": "stepped" },
					{ "time": 0.8333, "angle": 0, "curve": "stepped" },
					{ "time": 1, "angle": 0, "curve": "stepped" },
					{ "time": 1.1667, "angle": 0 }
				],
				"translate": [
					{ "time": 0, "x": 0, "y": 0, "curve": "stepped" },
					{ "time": 0.1667, "x": 0, "y": 0, "curve": "stepped" },
					{ "time": 0.3333, "x": 0, "y": 0, "curve": "stepped" },
					{ "time": 0.5, "x": 0, "y": 0, "curve": "stepped" },
					{ "time": 0.6667, "x": 0, "y": 0, "curve": "stepped" },
					{ "time": 0.8333, "x": 0, "y": 0, "curve": "stepped" },
					{ "time": 1, "x": 0, "y": 0, "curve": "stepped" },
					{ "time": 1.1667, "x": 0, "y": 0 }
				],
				"scale": [
					{ "time": 0, "x": 1, "y": 1, "curve": "stepped" },
					{ "time": 0.1667, "x": 1, "y": 1, "curve": "stepped" },
					{ "time": 0.3333, "x": 1, "y": 1, "curve": "stepped" },
					{ "time": 0.5, "x": 1, "y": 1, "curve": "stepped" },
					{ "time": 0.6667, "x": 1, "y": 1, "curve": "stepped" },
					{ "time": 0.8333, "x": 1, "y": 1, "curve": "stepped" },
					{ "time": 1, "x": 1, "y": 1, "curve": "stepped" },
					{ "time": 1.1667, "x": 1, "y": 1 }
				]
			}
		}
	}
}
}